{"head":{"vars":["p","pLabel","pAlias","pContent","pNationality","pWikilink","pPicture"]},"results":{"bindings":[{"p":{"type":"uri","value":"http://www.wikidata.org/entity/Q3166"},"pWikilink":{"type":"uri","value":"https://en.wikipedia.org/wiki/Denny%20Hulme"},"pPicture":{"type":"uri","value":"http://commons.wikimedia.org/wiki/Special:FilePath/HulmeDenis196508.jpg"},"pLabel":{"xml:lang":"en","type":"literal","value":"Denny Hulme"},"pContent":{"xml:lang":"en","type":"literal","value":"New Zealander racing driver"},"pAlias":{"xml:lang":"en","type":"literal","value":"Denis Clive Hulme"}},{"p":{"type":"uri","value":"http://www.wikidata.org/entity/Q1703469"},"pWikilink":{"type":"uri","value":"https://en.wikipedia.org/wiki/Jonny%20Reid"},"pPicture":{"type":"uri","value":"http://commons.wikimedia.org/wiki/Special:FilePath/Jonny%20Reid.JPG"},"pLabel":{"xml:lang":"en","type":"literal","value":"Jonny Reid"},"pContent":{"xml:lang":"en","type":"literal","value":"New Zealand racing driver"}},{"p":{"type":"uri","value":"http://www.wikidata.org/entity/Q1790883"},"pWikilink":{"type":"uri","value":"https://en.wikipedia.org/wiki/Wade%20Cunningham"},"pPicture":{"type":"uri","value":"http://commons.wikimedia.org/wiki/Special:FilePath/WadeCunningham2005.jpg"},"pLabel":{"xml:lang":"en","type":"literal","value":"Wade Cunningham"},"pContent":{"xml:lang":"en","type":"literal","value":"New Zealand racing driver"}},{"p":{"type":"uri","value":"http://www.wikidata.org/entity/Q171469"},"pWikilink":{"type":"uri","value":"https://en.wikipedia.org/wiki/Chris%20Amon"},"pPicture":{"type":"uri","value":"http://commons.wikimedia.org/wiki/Special:FilePath/AmonChris19730706.jpg"},"pLabel":{"xml:lang":"en","type":"literal","value":"Chris Amon"},"pContent":{"xml:lang":"en","type":"literal","value":"New Zealander racecar driver"},"pAlias":{"xml:lang":"en","type":"literal","value":"Christopher Amon, Christopher Arthur Amon"}},{"p":{"type":"uri","value":"http://www.wikidata.org/entity/Q171733"},"pWikilink":{"type":"uri","value":"https://en.wikipedia.org/wiki/Howden%20Ganley"},"pPicture":{"type":"uri","value":"http://commons.wikimedia.org/wiki/Special:FilePath/HowdenGanleyNZFMR2015.jpg"},"pLabel":{"xml:lang":"en","type":"literal","value":"Howden Ganley"},"pContent":{"xml:lang":"en","type":"literal","value":"racecar driver"}},{"p":{"type":"uri","value":"http://www.wikidata.org/entity/Q171752"},"pWikilink":{"type":"uri","value":"https://en.wikipedia.org/wiki/Mike%20Thackwell"},"pLabel":{"xml:lang":"en","type":"literal","value":"Mike Thackwell"},"pContent":{"xml:lang":"en","type":"literal","value":"New Zealander racecar driver"}},{"p":{"type":"uri","value":"http://www.wikidata.org/entity/Q171986"},"pWikilink":{"type":"uri","value":"https://en.wikipedia.org/wiki/John%20Nicholson%20%28racing%20driver%29"},"pLabel":{"xml:lang":"en","type":"literal","value":"John Nicholson"},"pContent":{"xml:lang":"en","type":"literal","value":"New Zealand racing driver"}},{"p":{"type":"uri","value":"http://www.wikidata.org/entity/Q1077911"},"pWikilink":{"type":"uri","value":"https://en.wikipedia.org/wiki/Chris%20van%20der%20Drift"},"pPicture":{"type":"uri","value":"http://commons.wikimedia.org/wiki/Special:FilePath/Chris%20van%20der%20Drift%20with%20his%20podium%20trophies%20at%20SF%202010.jpg"},"pLabel":{"xml:lang":"en","type":"literal","value":"Chris van der Drift"},"pContent":{"xml:lang":"en","type":"literal","value":"New Zealand racing driver"}},{"p":{"type":"uri","value":"http://www.wikidata.org/entity/Q1277000"},"pWikilink":{"type":"uri","value":"https://en.wikipedia.org/wiki/Earl%20Bamber"},"pLabel":{"xml:lang":"en","type":"literal","value":"Earl Bamber"},"pContent":{"xml:lang":"en","type":"literal","value":"racing driver, 2015 Le Mans winner, 2014 Porsche Supercup champion"},"pAlias":{"xml:lang":"en","type":"literal","value":"Earl Anderson Bamber"}},{"p":{"type":"uri","value":"http://www.wikidata.org/entity/Q6221992"},"pWikilink":{"type":"uri","value":"https://en.wikipedia.org/wiki/Shane%20van%20Gisbergen"},"pLabel":{"xml:lang":"en","type":"literal","value":"Shane Van Gisbergen"},"pContent":{"xml:lang":"en","type":"literal","value":"New Zealander racecar driver"}},{"p":{"type":"uri","value":"http://www.wikidata.org/entity/Q7436838"},"pWikilink":{"type":"uri","value":"https://en.wikipedia.org/wiki/Scott%20McLaughlin%20%28racing%20driver%29"},"pLabel":{"xml:lang":"en","type":"literal","value":"Scott McLaughlin"},"pContent":{"xml:lang":"en","type":"literal","value":"New Zealand racing driver"}},{"p":{"type":"uri","value":"http://www.wikidata.org/entity/Q7520063"},"pWikilink":{"type":"uri","value":"https://en.wikipedia.org/wiki/Simon%20Wills"},"pLabel":{"xml:lang":"en","type":"literal","value":"Simon Wills"},"pContent":{"xml:lang":"en","type":"literal","value":"New Zealand racing driver"}},{"p":{"type":"uri","value":"http://www.wikidata.org/entity/Q7613527"},"pWikilink":{"type":"uri","value":"https://en.wikipedia.org/wiki/Steve%20Owen%20%28racing%20driver%29"},"pPicture":{"type":"uri","value":"http://commons.wikimedia.org/wiki/Special:FilePath/Steve%20Owen.jpg"},"pLabel":{"xml:lang":"en","type":"literal","value":"Steve Owen"},"pContent":{"xml:lang":"en","type":"literal","value":"Australian racing driver"}},{"p":{"type":"uri","value":"http://www.wikidata.org/entity/Q7659703"},"pWikilink":{"type":"uri","value":"https://en.wikipedia.org/wiki/Syd%20Jensen"},"pLabel":{"xml:lang":"en","type":"literal","value":"Syd Jensen"},"pContent":{"xml:lang":"en","type":"literal","value":"New Zealand motorcycle racer"}},{"p":{"type":"uri","value":"http://www.wikidata.org/entity/Q7793181"},"pWikilink":{"type":"uri","value":"https://en.wikipedia.org/wiki/Thomas%20Pitt%20Cholmondeley-Tapper"},"pLabel":{"xml:lang":"en","type":"literal","value":"Thomas Pitt Cholmondeley-Tapper"},"pContent":{"xml:lang":"en","type":"literal","value":"New Zealand racing driver"}},{"p":{"type":"uri","value":"http://www.wikidata.org/entity/Q7925796"},"pWikilink":{"type":"uri","value":"https://en.wikipedia.org/wiki/Victor%20Chapman%20%28racing%20driver%29"},"pLabel":{"xml:lang":"en","type":"literal","value":"Victor Chapman"},"pContent":{"xml:lang":"en","type":"literal","value":"New Zealand racing driver"}},{"p":{"type":"uri","value":"http://www.wikidata.org/entity/Q15993625"},"pWikilink":{"type":"uri","value":"https://en.wikipedia.org/wiki/Bob%20Wallace%20%28test%20driver%29"},"pPicture":{"type":"uri","value":"http://commons.wikimedia.org/wiki/Special:FilePath/Bob%20Wallace%20working%20on%20Maserati%20Birdcage%2C%201960s.jpg"},"pLabel":{"xml:lang":"en","type":"literal","value":"Bob Wallace"},"pContent":{"xml:lang":"en","type":"literal","value":"New Zealand test driver"}},{"p":{"type":"uri","value":"http://www.wikidata.org/entity/Q172535"},"pWikilink":{"type":"uri","value":"https://en.wikipedia.org/wiki/Graham%20McRae"},"pLabel":{"xml:lang":"en","type":"literal","value":"Graham McRae"},"pContent":{"xml:lang":"en","type":"literal","value":"New Zealand racing driver"}},{"p":{"type":"uri","value":"http://www.wikidata.org/entity/Q173081"},"pWikilink":{"type":"uri","value":"https://en.wikipedia.org/wiki/Bruce%20McLaren"},"pPicture":{"type":"uri","value":"http://commons.wikimedia.org/wiki/Special:FilePath/McLarenBruce.jpg"},"pLabel":{"xml:lang":"en","type":"literal","value":"Bruce McLaren"},"pContent":{"xml:lang":"en","type":"literal","value":"New Zealander racecar driver, designer and team owner"},"pAlias":{"xml:lang":"en","type":"literal","value":"Bruce Leslie McLaren"}},{"p":{"type":"uri","value":"http://www.wikidata.org/entity/Q361113"},"pWikilink":{"type":"uri","value":"https://en.wikipedia.org/wiki/Brendon%20Hartley"},"pPicture":{"type":"uri","value":"http://commons.wikimedia.org/wiki/Special:FilePath/Brendon%20Hartley%20Driver%20of%20Porsche%20Team%27s%20Porsche%20919%20Hybrid.jpg"},"pLabel":{"xml:lang":"en","type":"literal","value":"Brendon Hartley"},"pContent":{"xml:lang":"en","type":"literal","value":"racing driver, 2015 World Endurance Drivers' Champion"},"pAlias":{"xml:lang":"en","type":"literal","value":"Hartley, Brendon"}},{"p":{"type":"uri","value":"http://www.wikidata.org/entity/Q389092"},"pWikilink":{"type":"uri","value":"https://en.wikipedia.org/wiki/Alex%20Davison"},"pLabel":{"xml:lang":"en","type":"literal","value":"Alex Davison"},"pContent":{"xml:lang":"en","type":"literal","value":"Australian racecar driver"}},{"p":{"type":"uri","value":"http://www.wikidata.org/entity/Q465201"},"pWikilink":{"type":"uri","value":"https://en.wikipedia.org/wiki/Scott%20Dixon"},"pPicture":{"type":"uri","value":"http://commons.wikimedia.org/wiki/Special:FilePath/Scott%20Dixon%20at%20the%202013%20Grand%20Prix%20of%20Baltimore.jpg"},"pLabel":{"xml:lang":"en","type":"literal","value":"Scott Dixon"},"pContent":{"xml:lang":"en","type":"literal","value":"New Zealander racecar driver"}},{"p":{"type":"uri","value":"http://www.wikidata.org/entity/Q735803"},"pWikilink":{"type":"uri","value":"https://en.wikipedia.org/wiki/Mitch%20Evans"},"pPicture":{"type":"uri","value":"http://commons.wikimedia.org/wiki/Special:FilePath/Dallara%20F307%20of%20Mitch%20Evans.jpg"},"pLabel":{"xml:lang":"en","type":"literal","value":"Mitch Evans"},"pContent":{"xml:lang":"en","type":"literal","value":"New Zealand racing driver"}},{"p":{"type":"uri","value":"http://www.wikidata.org/entity/Q3001990"},"pWikilink":{"type":"uri","value":"https://en.wikipedia.org/wiki/Craig%20Baird"},"pLabel":{"xml:lang":"en","type":"literal","value":"Craig Baird"},"pContent":{"xml:lang":"en","type":"literal","value":"New Zealand racing driver"}},{"p":{"type":"uri","value":"http://www.wikidata.org/entity/Q4756254"},"pWikilink":{"type":"uri","value":"https://en.wikipedia.org/wiki/Andrew%20Bagnall"},"pLabel":{"xml:lang":"en","type":"literal","value":"Andrew Bagnall"},"pContent":{"xml:lang":"en","type":"literal","value":"New Zealand racing driver"}},{"p":{"type":"uri","value":"http://www.wikidata.org/entity/Q4933009"},"pWikilink":{"type":"uri","value":"https://en.wikipedia.org/wiki/Bob%20Kennett"},"pLabel":{"xml:lang":"en","type":"literal","value":"Bob Kennett"},"pContent":{"xml:lang":"en","type":"literal","value":"New Zealand racing driver"}},{"p":{"type":"uri","value":"http://www.wikidata.org/entity/Q5040737"},"pWikilink":{"type":"uri","value":"https://en.wikipedia.org/wiki/Carl%20Ruiterman"},"pLabel":{"xml:lang":"en","type":"literal","value":"Carl Ruiterman"},"pContent":{"xml:lang":"en","type":"literal","value":"New Zealand racing driver"}},{"p":{"type":"uri","value":"http://www.wikidata.org/entity/Q5229361"},"pWikilink":{"type":"uri","value":"https://en.wikipedia.org/wiki/Dave%20McMillan"},"pLabel":{"xml:lang":"en","type":"literal","value":"Dave McMillan"},"pContent":{"xml:lang":"en","type":"literal","value":"New Zealand racing driver"}},{"p":{"type":"uri","value":"http://www.wikidata.org/entity/Q5592317"},"pWikilink":{"type":"uri","value":"https://en.wikipedia.org/wiki/Graeme%20Lawrence"},"pLabel":{"xml:lang":"en","type":"literal","value":"Graeme Lawrence"},"pContent":{"xml:lang":"en","type":"literal","value":"New Zealand racing driver"}}]}}