{"head":{"vars":["country","countryLabel","countryContent","countryAlias","countryWikilink","capital","capitalLabel","capitalContent","capitalAlias","capitalWikilink"]},"results":{"bindings":[{"country":{"type":"uri","value":"http://www.wikidata.org/entity/Q408"},"countryLabel":{"xml:lang":"en","type":"literal","value":"Australia"},"countryContent":{"xml:lang":"en","type":"literal","value":"constitutional monarchy in Oceania"},"countryAlias":{"xml:lang":"en","type":"literal","value":"AU, AUS, au, British Colony of Australia, Commonwealth of Australia"},"countryWikilink":{"type":"uri","value":"https://en.wikipedia.org/wiki/Australia"},"capital":{"type":"uri","value":"http://www.wikidata.org/entity/Q3114"},"capitalLabel":{"xml:lang":"en","type":"literal","value":"Canberra"},"capitalContent":{"xml:lang":"en","type":"literal","value":"capital city of Australia"}},{"country":{"type":"uri","value":"http://www.wikidata.org/entity/Q702"},"countryLabel":{"xml:lang":"en","type":"literal","value":"Federated States of Micronesia"},"countryContent":{"xml:lang":"en","type":"literal","value":"country in Oceania"},"countryAlias":{"xml:lang":"en","type":"literal","value":"FSM, fm, Micronesia, Fed. Sts. Micronesia, Fed. Sts. of Micronesia, Federated States of Micronesia, FSM, 🇫🇲"},"countryWikilink":{"type":"uri","value":"https://en.wikipedia.org/wiki/Federated%20States%20of%20Micronesia"},"capital":{"type":"uri","value":"http://www.wikidata.org/entity/Q42751"},"capitalLabel":{"xml:lang":"en","type":"literal","value":"Palikir"},"capitalContent":{"xml:lang":"en","type":"literal","value":"capital of Federated States of Micronesia"}},{"country":{"type":"uri","value":"http://www.wikidata.org/entity/Q712"},"countryLabel":{"xml:lang":"en","type":"literal","value":"Fiji"},"countryContent":{"xml:lang":"en","type":"literal","value":"country in Oceania"},"countryAlias":{"xml:lang":"en","type":"literal","value":"fj, Republic of Fiji, 🇫🇯"},"countryWikilink":{"type":"uri","value":"https://en.wikipedia.org/wiki/Fiji"},"capital":{"type":"uri","value":"http://www.wikidata.org/entity/Q38807"},"capitalLabel":{"xml:lang":"en","type":"literal","value":"Suva"},"capitalContent":{"xml:lang":"en","type":"literal","value":"capital city of Fiji"}},{"country":{"type":"uri","value":"http://www.wikidata.org/entity/Q710"},"countryLabel":{"xml:lang":"en","type":"literal","value":"Kiribati"},"countryContent":{"xml:lang":"en","type":"literal","value":"island nation in the central Pacific Ocean"},"countryAlias":{"xml:lang":"en","type":"literal","value":"Republic of Kiribati, 🇰🇮"},"countryWikilink":{"type":"uri","value":"https://en.wikipedia.org/wiki/Kiribati"},"capital":{"type":"uri","value":"http://www.wikidata.org/entity/Q131233"},"capitalLabel":{"xml:lang":"en","type":"literal","value":"South Tarawa"},"capitalContent":{"xml:lang":"en","type":"literal","value":"capital of Kiribati"}},{"country":{"type":"uri","value":"http://www.wikidata.org/entity/Q709"},"countryLabel":{"xml:lang":"en","type":"literal","value":"Marshall Islands"},"countryContent":{"xml:lang":"en","type":"literal","value":"country in Oceania"},"countryAlias":{"xml:lang":"en","type":"literal","value":"mh, Aolepān Aorōkin M̧ajeļ, Republic of the Marshall Islands, 🇲🇭"},"countryWikilink":{"type":"uri","value":"https://en.wikipedia.org/wiki/Marshall%20Islands"},"capital":{"type":"uri","value":"http://www.wikidata.org/entity/Q12919"},"capitalLabel":{"xml:lang":"en","type":"literal","value":"Majuro"},"capitalContent":{"xml:lang":"en","type":"literal","value":"coral atoll, capital of the Marshall Islands"},"capitalAlias":{"xml:lang":"en","type":"literal","value":"Mājro"}},{"country":{"type":"uri","value":"http://www.wikidata.org/entity/Q697"},"countryLabel":{"xml:lang":"en","type":"literal","value":"Nauru"},"countryContent":{"xml:lang":"en","type":"literal","value":"republic in Oceania"},"countryAlias":{"xml:lang":"en","type":"literal","value":"Naoero, nr, Pleasant Island, Republic of Nauru, 🇳🇷"},"countryWikilink":{"type":"uri","value":"https://en.wikipedia.org/wiki/Nauru"},"capital":{"type":"uri","value":"http://www.wikidata.org/entity/Q31026"},"capitalLabel":{"xml:lang":"en","type":"literal","value":"Yaren District"},"capitalContent":{"xml:lang":"en","type":"literal","value":"district and de facto capital of Nauru"},"capitalAlias":{"xml:lang":"en","type":"literal","value":"Makwa, Yaren, Moqua"}},{"country":{"type":"uri","value":"http://www.wikidata.org/entity/Q664"},"countryLabel":{"xml:lang":"en","type":"literal","value":"New Zealand"},"countryContent":{"xml:lang":"en","type":"literal","value":"constitutional monarchy in Oceania"},"countryAlias":{"xml:lang":"en","type":"literal","value":"Aotearoa, Dominion of New Zealand, nz, NZ, NZL, 🇳🇿"},"countryWikilink":{"type":"uri","value":"https://en.wikipedia.org/wiki/New%20Zealand"},"capital":{"type":"uri","value":"http://www.wikidata.org/entity/Q23661"},"capitalLabel":{"xml:lang":"en","type":"literal","value":"Wellington"},"capitalContent":{"xml:lang":"en","type":"literal","value":"capital city of New Zealand"},"capitalAlias":{"xml:lang":"en","type":"literal","value":"Te Whanga-nui-a-Tara, Wellington, New Zealand, Wellington, NZ"}},{"country":{"type":"uri","value":"http://www.wikidata.org/entity/Q34020"},"countryLabel":{"xml:lang":"en","type":"literal","value":"Niue"},"countryContent":{"xml:lang":"en","type":"literal","value":"island country in the South Pacific Ocean"},"countryAlias":{"xml:lang":"en","type":"literal","value":"nu, Niuē, 🇳🇺"},"countryWikilink":{"type":"uri","value":"https://en.wikipedia.org/wiki/Niue"},"capital":{"type":"uri","value":"http://www.wikidata.org/entity/Q30966"},"capitalLabel":{"xml:lang":"en","type":"literal","value":"Alofi"},"capitalContent":{"xml:lang":"en","type":"literal","value":"capital city of Niue"},"capitalAlias":{"xml:lang":"en","type":"literal","value":"Alofi, Niue"}},{"country":{"type":"uri","value":"http://www.wikidata.org/entity/Q695"},"countryLabel":{"xml:lang":"en","type":"literal","value":"Palau"},"countryContent":{"xml:lang":"en","type":"literal","value":"republic in Oceania"},"countryAlias":{"xml:lang":"en","type":"literal","value":"Belau, Pelew, pw, Republic of Belau, Republic of Palau, 🇵🇼"},"countryWikilink":{"type":"uri","value":"https://en.wikipedia.org/wiki/Palau"},"capital":{"type":"uri","value":"http://www.wikidata.org/entity/Q515229"},"capitalLabel":{"xml:lang":"en","type":"literal","value":"Ngerulmud"},"capitalContent":{"xml:lang":"en","type":"literal","value":"capital of Palau"}},{"country":{"type":"uri","value":"http://www.wikidata.org/entity/Q691"},"countryLabel":{"xml:lang":"en","type":"literal","value":"Papua New Guinea"},"countryContent":{"xml:lang":"en","type":"literal","value":"republic in Oceania"},"countryAlias":{"xml:lang":"en","type":"literal","value":"pg, PNG, Independent State of Papua New Guinea, 🇵🇬"},"countryWikilink":{"type":"uri","value":"https://en.wikipedia.org/wiki/Papua%20New%20Guinea"},"capital":{"type":"uri","value":"http://www.wikidata.org/entity/Q36526"},"capitalLabel":{"xml:lang":"en","type":"literal","value":"Port Moresby"},"capitalContent":{"xml:lang":"en","type":"literal","value":"capital of Papua New Guinea"}},{"country":{"type":"uri","value":"http://www.wikidata.org/entity/Q683"},"countryLabel":{"xml:lang":"en","type":"literal","value":"Samoa"},"countryContent":{"xml:lang":"en","type":"literal","value":"country in Oceania"},"countryAlias":{"xml:lang":"en","type":"literal","value":"ws, Independent State of Samoa, Western Samoa, 🇼🇸"},"countryWikilink":{"type":"uri","value":"https://en.wikipedia.org/wiki/Samoa"},"capital":{"type":"uri","value":"http://www.wikidata.org/entity/Q36260"},"capitalLabel":{"xml:lang":"en","type":"literal","value":"Apia"},"capitalContent":{"xml:lang":"en","type":"literal","value":"capital of Samoa"}},{"country":{"type":"uri","value":"http://www.wikidata.org/entity/Q685"},"countryLabel":{"xml:lang":"en","type":"literal","value":"Solomon Islands"},"countryContent":{"xml:lang":"en","type":"literal","value":"country in Oceania"},"countryAlias":{"xml:lang":"en","type":"literal","value":"sb, 🇸🇧"},"countryWikilink":{"type":"uri","value":"https://en.wikipedia.org/wiki/Solomon%20Islands"},"capital":{"type":"uri","value":"http://www.wikidata.org/entity/Q40921"},"capitalLabel":{"xml:lang":"en","type":"literal","value":"Honiara"},"capitalContent":{"xml:lang":"en","type":"literal","value":"capital of Solomon Islands, on the tropical island Guadalcanal"}},{"country":{"type":"uri","value":"http://www.wikidata.org/entity/Q678"},"countryLabel":{"xml:lang":"en","type":"literal","value":"Tonga"},"countryContent":{"xml:lang":"en","type":"literal","value":"country in Oceania"},"countryAlias":{"xml:lang":"en","type":"literal","value":"🇹🇴"},"countryWikilink":{"type":"uri","value":"https://en.wikipedia.org/wiki/Tonga"},"capital":{"type":"uri","value":"http://www.wikidata.org/entity/Q38834"},"capitalLabel":{"xml:lang":"en","type":"literal","value":"Nuku'alofa"},"capitalContent":{"xml:lang":"en","type":"literal","value":"capital city of Tonga"}},{"country":{"type":"uri","value":"http://www.wikidata.org/entity/Q672"},"countryLabel":{"xml:lang":"en","type":"literal","value":"Tuvalu"},"countryContent":{"xml:lang":"en","type":"literal","value":"country in Oceania"},"countryAlias":{"xml:lang":"en","type":"literal","value":"Ellice Islands, tv, 🇹🇻"},"countryWikilink":{"type":"uri","value":"https://en.wikipedia.org/wiki/Tuvalu"},"capital":{"type":"uri","value":"http://www.wikidata.org/entity/Q34126"},"capitalLabel":{"xml:lang":"en","type":"literal","value":"Funafuti"},"capitalContent":{"xml:lang":"en","type":"literal","value":"atoll and capital of Tuvalu"},"capitalAlias":{"xml:lang":"en","type":"literal","value":"Funafuti Island"}},{"country":{"type":"uri","value":"http://www.wikidata.org/entity/Q30"},"countryLabel":{"xml:lang":"en","type":"literal","value":"United States of America"},"countryContent":{"xml:lang":"en","type":"literal","value":"federal republic in North America"},"countryAlias":{"xml:lang":"en","type":"literal","value":"America, US, United States, USA, U.S., 🇺🇸, U.S.A., the States, the US"},"countryWikilink":{"type":"uri","value":"https://en.wikipedia.org/wiki/United%20States"},"capital":{"type":"uri","value":"http://www.wikidata.org/entity/Q61"},"capitalLabel":{"xml:lang":"en","type":"literal","value":"Washington, D.C."},"capitalContent":{"xml:lang":"en","type":"literal","value":"capital city of the United States"},"capitalAlias":{"xml:lang":"en","type":"literal","value":"Washington, DC, D.C., District of Columbia, the District, Washington DC, Washington, DC"}},{"country":{"type":"uri","value":"http://www.wikidata.org/entity/Q686"},"countryLabel":{"xml:lang":"en","type":"literal","value":"Vanuatu"},"countryContent":{"xml:lang":"en","type":"literal","value":"country in Oceania"},"countryAlias":{"xml:lang":"en","type":"literal","value":"Republic of Vanuatu, vu, 🇻🇺"},"countryWikilink":{"type":"uri","value":"https://en.wikipedia.org/wiki/Vanuatu"},"capital":{"type":"uri","value":"http://www.wikidata.org/entity/Q37806"},"capitalLabel":{"xml:lang":"en","type":"literal","value":"Port Vila"},"capitalContent":{"xml:lang":"en","type":"literal","value":"capital and largest city of Vanuatu"}}]}}